hic_sca-0.2.4.dist-info/licenses/LICENSE
hicsca/__init__.py
hicsca/evals.py
hicsca/formats.py
hicsca/hicsca.py
hicsca/hicsca_cli.py
hic_sca-0.2.4.dist-info/METADATA
hic_sca-0.2.4.dist-info/WHEEL
hic_sca-0.2.4.dist-info/entry_points.txt
hic_sca-0.2.4.dist-info/top_level.txt
hic_sca-0.2.4.dist-info/RECORD
