Metadata-Version: 2.4
Name: hic-sca
Version: 0.2.4
Summary: HiC-SCA: Hi-C Spectral Compartment Assignment for predicting A-B chromosomal compartments
Author-email: Justin Chan <chan.waisoon@qst.go.jp>, Hidetoshi Kono <kono.hidetoshi@qst.go.jp>
License-Expression: MIT
Project-URL: Homepage, https://github.com/iQLS-MMS/hic-sca
Classifier: Development Status :: 4 - Beta
Classifier: Intended Audience :: Science/Research
Classifier: Topic :: Scientific/Engineering :: Bio-Informatics
Classifier: Programming Language :: Python :: 3
Classifier: Programming Language :: Python :: 3.10
Classifier: Programming Language :: Python :: 3.11
Classifier: Programming Language :: Python :: 3.12
Classifier: Programming Language :: Python :: 3.13
Classifier: Programming Language :: Python :: 3.14
Classifier: Operating System :: MacOS :: MacOS X
Classifier: Operating System :: POSIX :: Linux
Requires-Python: >=3.10
License-File: LICENSE
Requires-Dist: numpy>=1.19.0
Requires-Dist: scipy>=1.15.0
Requires-Dist: hic-straw>=1.3.0
Requires-Dist: h5py>=3.0.0
Requires-Dist: matplotlib>=3.0.0
Requires-Dist: pandas>=1.3.0
Requires-Dist: openpyxl>=3.0.0
Requires-Dist: h5typer>=0.1.0
Provides-Extra: tests
Requires-Dist: pytest>=6.0; extra == "tests"
Dynamic: license-file
